Workbook

Sheet Plan1
A3: POLYESTER 120 | C3: AREA DE IMPRESSÃO EM M QUADRADO | D3: TEMPO GASTO EM HORAS E MINUTOS P/MIL | E3: QUANTIDADE DE TINTA PREVISTA EM M 2 | F3: QUANTIDADE DE SOLVENTE PREVISTO | G3: CUSTO DA MÃO DE OBRA | H3: QUANTIDADE DE SACOLA | I3: VALOR DA TINTA | J3: 200 ML DE SOLVENTE | K3: ENERGIA | L3: energia
A4: TINTA POLYETILENO
L5: limpeza de matrizes
A9: CUSTO POR MIL | C9: =0.25*0.25 -> 0.0625 | D9: =0.12*H9/60 -> 2 | E9: =C9*H9 -> 62.5 | F9: 50 | G9: =3500/30/8*D9 -> 29.166667 | H9: 1000 | I9: 140 | J9: =F9/50 -> 1 | K9: =1.2*D9 -> 2.4 | L9: =40/10 -> 4
B10: 1 COR | C10: =(G9+I9+J9+K9+L9) -> 176.56667
B11: 2 CORES | C11: =(G9+I9+J9+K9)*2 -> 345.13333
B12: 3 CORES | C12: =(G9+I9+J9+K9)*3 -> 517.7
B13: 4 CORES | C13: =(G9+I9+J9+K9)*4 -> 690.26667
I1046604: =

Sheet Plan2
B2: SACOLA TAMANHO E MODELOS | G2: vlr/kg | H2: % | I2: SACOLA TAMANHO E MODELOS
B3: kg/1000 | C3: Tamanho | D3: ESPESSURA | E3: MODELO | F3: PREÇO de compra | G3: =Plan3!F2 -> 40 | H3: 0.35 | I3: TAMANHO | J3: COR | K3: ESPESSURA | L3: MODELO | M3: PREÇO | N3: QUANT.
B4: =17*24*0.011 -> 4.488 | C4: 17x24 | D4: 0.011 | E4: ALÇA C | F4: =B4*$G$3 -> 179.52 | G4: =F4/(1-$H$3) -> 276.18462 | I4: 12 | J4: BRANCA | K4: 0.01 | L4: ALÇA C | M4: =I4*15*1.3 -> 234
B5: =15*25*0.01 -> 3.75 | C5: 15X25 | D5: 0.01 | E5: ALÇA C | F5: =B5*$G$3 -> 150 | G5: =F5/(1-$H$3) -> 230.76923 | I5: 8.1 | J5: BRANCA | K5: 0.005 | L5: CAMISETA | M5: =I5*39.9*1.3 -> 420.147
B6: =20*30*0.01 -> 6 | C6: 20X30 | D6: 0.01 | E6: ALÇA C | F6: =B6*$G$3 -> 240 | G6: =F6/(1-$H$3) -> 369.23077
B7: =25*35*0.01 -> 8.75 | C7: 25X35 | D7: 0.01 | E7: ALÇA C | F7: =B7*$G$3 -> 350 | G7: =F7/(1-$H$3) -> 538.46154
B8: =30*40*0.011 -> 13.2 | C8: 30X40 | D8: 0.01 | E8: ALÇA C | F8: =B8*$G$3 -> 528 | G8: =F8/(1-$H$3) -> 812.30769
B9: =30*45*0.01 -> 13.5 | C9: 30x45 | D9: 0.01 | E9: ALÇA C | F9: =B9*$G$3 -> 540 | G9: =F9/(1-$H$3) -> 830.76923
B10: =35*50*0.01 -> 17.5 | C10: 35x50 | D10: 0.01 | E10: ALÇA C | F10: =B10*$G$3 -> 700 | G10: =F10/(1-$H$3) -> 1076.9231
B11: =40*50*0.01 -> 20 | C11: 40X50 | D11: 0.01 | E11: ALÇA C | F11: =B11*$G$3 -> 800 | G11: =F11/(1-$H$3) -> 1230.7692
B12: =40*60*0.01 -> 24 | C12: 40X60 | D12: 0.01 | E12: ALÇA C | F12: =B12*$G$3 -> 960 | G12: =F12/(1-$H$3) -> 1476.9231
B13: =45*60*0.01 -> 27 | C13: 45x60 | D13: 0.01 | E13: ALÇA C | F13: =B13*$G$3 -> 1080 | G13: =F13/(1-$H$3) -> 1661.5385
B15: =30*32*0.006 -> 5.76 | C15: 30x32 | D15: 0.006 | E15: CAMISETA | F15: =B15*$G$3 -> 230.4 | G15: =F15/(1-$H$3) -> 354.46154
B16: =30*45*0.006 -> 8.1 | C16: 30x45 | D16: 0.006 | E16: CAMISETA | F16: =B16*$G$3 -> 324 | G16: =F16/(1-$H$3) -> 498.46154
B17: =40*50*0.006 -> 12 | C17: BRANCA | D17: 0.006 | E17: CAMISETA | F17: =B17*$G$3 -> 480 | G17: =F17/(1-$H$3) -> 738.46154
B18: =40*60*0.006 -> 14.4 | C18: BRANCA | D18: 0.006 | E18: CAMISETA | F18: =B18*$G$3 -> 576 | G18: =F18/(1-$H$3) -> 886.15385 | J18: TINTA
B19: =50*70*0.005 -> 17.5 | C19: BRANCA | D19: 0.005 | E19: CAMISETA | F19: =B19*$G$3 -> 700 | G19: =F19/(1-$H$3) -> 1076.9231 | J19: SACOLA
B20: =60*80*0.005 -> 24 | C20: BRANCA | D20: 0.005 | E20: CAMISETA | F20: =B20*$G$3 -> 960 | G20: =F20/(1-$H$3) -> 1476.9231 | J20: SOLVENTE
B21: =45*60*0.006 -> 16.2 | C21: BRANCA | D21: 0.005 | E21: CAMISETA | F21: =B21*$G$3 -> 648 | G21: =F21/(1-$H$3) -> 996.92308 | J21: MÃO DE OBRA
J22: ENERGIA

Sheet Plan3
B2: ALÇA C OU BOCA DE PALHAÇO | C2: FORNECEDOR | E2: 2 IRMÃO | F2: =VLOOKUP(E2,K30:L33,2,0) -> 40 | H2: ESPESSURA | I2: UNIDADES | J2: 500 1 COR | K2: 500 2 CORES | L2: 500 3 CORES | M2: 500 4 CORES | N2: ALÇA C OU BOCA DE PALHAÇO | P2: 250 1 COR | Q2: 250 2 CORES | R2: 250 3 CORES | S2: 250 4 CORES | U2: 125 1 COR | V2: 125 2 CORES | W2: 125 3 CORES | X2: 125 4 CORES | Y2: espessura | Z2: 60 1 COR | AA2: 60 2 CORES | AB2: 60 3 CORES | AC2: 60 4 CORES
C4: TAMANHO | D4: 1 COR | E4: 2 CORES | F4: 3 CORES | G4: 4 CORES
C5: 17x24 | D5: =Plan1!$C$10+Plan2!G4 -> 452.75128 | E5: =Plan1!$C$11+Plan2!G4 -> 621.31795 | F5: =Plan1!$C$12+Plan2!G4 -> 793.88462 | G5: =Plan1!$C$13+Plan2!G4 -> 966.45128 | H5: 0.01 | I5: 15x20 | J5: =D5/1.6 -> 282.96955 | K5: =E5/1.6 -> 388.32372 | L5: =F5/1.6 -> 496.17788 | M5: =G5/1.6 -> 604.03205 | O5: 15x20 | P5: =J5/1.6 -> 176.85597 | Q5: =K5/1.6 -> 242.70232 | R5: =L5/1.6 -> 310.11118 | S5: =M5/1.6 -> 377.52003 | T5: 15x20 | U5: =P5/1.6 -> 110.53498 | V5: =Q5/1.6 -> 151.68895 | W5: =R5/1.6 -> 193.81949 | X5: =S5/1.6 -> 235.95002 | Y5: 0.01 | Z5: =U5/1.6 -> 69.084363 | AA5: =V5/1.6 -> 94.805595 | AB5: =W5/1.6 -> 121.13718 | AC5: =X5/1.6 -> 147.46876
C6: 15X25 | D6: =Plan1!$C$10+Plan2!G5 -> 407.3359 | E6: =Plan1!$C$11+Plan2!G5 -> 575.90256 | F6: =Plan1!$C$12+Plan2!G5 -> 748.46923 | G6: =Plan1!$C$13+Plan2!G5 -> 921.0359 | H6: 0.01 | I6: 15X25 | J6: =D6/1.6 -> 254.58494 | K6: =E6/1.6 -> 359.9391 | L6: =F6/1.6 -> 467.79327 | M6: =G6/1.6 -> 575.64744 | O6: 15X25 | P6: =J6/1.6 -> 159.11558 | Q6: =K6/1.6 -> 224.96194 | R6: =L6/1.6 -> 292.37079 | S6: =M6/1.6 -> 359.77965 | T6: 15X25 | U6: =P6/1.6 -> 99.447241 | V6: =Q6/1.6 -> 140.60121 | W6: =R6/1.6 -> 182.73175 | X6: =S6/1.6 -> 224.86228 | Y6: 0.01 | Z6: =U6/1.6 -> 62.154525 | AA6: =V6/1.6 -> 87.875757 | AB6: =W6/1.6 -> 114.20734 | AC6: =X6/1.6 -> 140.53892
C7: 20X30 | D7: =Plan1!$C$10+Plan2!G6 -> 545.79744 | E7: =Plan1!$C$11+Plan2!G6 -> 714.3641 | F7: =Plan1!$C$12+Plan2!G6 -> 886.93077 | G7: =Plan1!$C$13+Plan2!G6 -> 1059.4974 | H7: 0.01 | I7: 20X30 | J7: =D7/1.6 -> 341.1234 | K7: =E7/1.6 -> 446.47756 | L7: =F7/1.6 -> 554.33173 | M7: =G7/1.6 -> 662.1859 | O7: 20X30 | P7: =J7/1.6 -> 213.20212 | Q7: =K7/1.6 -> 279.04848 | R7: =L7/1.6 -> 346.45733 | S7: =M7/1.6 -> 413.86619 | T7: 20X30 | U7: =P7/1.6 -> 133.25133 | V7: =Q7/1.6 -> 174.4053 | W7: =R7/1.6 -> 216.53583 | X7: =S7/1.6 -> 258.66637 | Y7: 0.01 | Z7: =U7/1.6 -> 83.282079 | AA7: =V7/1.6 -> 109.00331 | AB7: =W7/1.6 -> 135.3349 | AC7: =X7/1.6 -> 161.66648
C8: 25X35 | D8: =Plan1!$C$10+Plan2!G7 -> 715.02821 | E8: =Plan1!$C$11+Plan2!G7 -> 883.59487 | F8: =Plan1!$C$12+Plan2!G7 -> 1056.1615 | G8: =Plan1!$C$13+Plan2!G7 -> 1228.7282 | H8: 0.01 | I8: 25X35 | J8: =D8/1.6 -> 446.89263 | K8: =E8/1.6 -> 552.24679 | L8: =F8/1.6 -> 660.10096 | M8: =G8/1.6 -> 767.95513 | O8: 25X35 | P8: =J8/1.6 -> 279.30789 | Q8: =K8/1.6 -> 345.15425 | R8: =L8/1.6 -> 412.5631 | S8: =M8/1.6 -> 479.97196 | T8: 25X35 | U8: =P8/1.6 -> 174.56743 | V8: =Q8/1.6 -> 215.7214 | W8: =R8/1.6 -> 257.85194 | X8: =S8/1.6 -> 299.98247 | Y8: 0.01 | Z8: =U8/1.6 -> 109.10465 | AA8: =V8/1.6 -> 134.82588 | AB8: =W8/1.6 -> 161.15746 | AC8: =X8/1.6 -> 187.48904
C9: 30X40 | D9: =Plan1!$C$10+Plan2!G8 -> 988.87436 | E9: =Plan1!$C$11+Plan2!G8 -> 1157.441 | F9: =Plan1!$C$12+Plan2!G8 -> 1330.0077 | G9: =Plan1!$C$13+Plan2!G8 -> 1502.5744 | H9: 0.01 | I9: 30X40 | J9: =D9/1.6 -> 618.04647 | K9: =E9/1.6 -> 723.40064 | L9: =F9/1.6 -> 831.25481 | M9: =G9/1.6 -> 939.10897 | O9: 30X40 | P9: =J9/1.6 -> 386.27905 | Q9: =K9/1.6 -> 452.1254 | R9: =L9/1.6 -> 519.53425 | S9: =M9/1.6 -> 586.94311 | T9: 30X40 | U9: =P9/1.6 -> 241.4244 | V9: =Q9/1.6 -> 282.57838 | W9: =R9/1.6 -> 324.70891 | X9: =S9/1.6 -> 366.83944 | Y9: 0.01 | Z9: =U9/1.6 -> 150.89025 | AA9: =V9/1.6 -> 176.61148 | AB9: =W9/1.6 -> 202.94307 | AC9: =X9/1.6 -> 229.27465
C10: 30x45 | D10: =Plan1!$C$10+Plan2!G9 -> 1007.3359 | E10: =Plan1!$C$11+Plan2!G9 -> 1175.9026 | F10: =Plan1!$C$12+Plan2!G9 -> 1348.4692 | G10: =Plan1!$C$13+Plan2!G9 -> 1521.0359 | H10: 0.01 | I10: 35x45 | J10: =D10/1.6 -> 629.58494 | K10: =E10/1.6 -> 734.9391 | L10: =F10/1.6 -> 842.79327 | M10: =G10/1.6 -> 950.64744 | O10: 35x45 | P10: =J10/1.6 -> 393.49058 | Q10: =K10/1.6 -> 459.33694 | R10: =L10/1.6 -> 526.74579 | S10: =M10/1.6 -> 594.15465 | T10: 35X50 | U10: =P10/1.6 -> 245.93162 | V10: =Q10/1.6 -> 287.08559 | W10: =R10/1.6 -> 329.21612 | X10: =S10/1.6 -> 371.34665 | Y10: 0.01 | Z10: =U10/1.6 -> 153.70726 | AA10: =V10/1.6 -> 179.42849 | AB10: =W10/1.6 -> 205.76008 | AC10: =X10/1.6 -> 232.09166
C11: 35x50 | D11: =Plan1!$C$10+Plan2!G10 -> 1253.4897 | E11: =Plan1!$C$11+Plan2!G10 -> 1422.0564 | F11: =Plan1!$C$12+Plan2!G10 -> 1594.6231 | G11: =Plan1!$C$13+Plan2!G10 -> 1767.1897 | H11: 0.01 | I11: 35x50 | J11: =D11/1.6 -> 783.43109 | K11: =E11/1.6 -> 888.78526 | L11: =F11/1.6 -> 996.63942 | M11: =G11/1.6 -> 1104.4936 | O11: 35x50 | P11: =J11/1.6 -> 489.64443 | Q11: =K11/1.6 -> 555.49079 | R11: =L11/1.6 -> 622.89964 | S11: =M11/1.6 -> 690.30849 | T11: 40X50 | U11: =P11/1.6 -> 306.02777 | V11: =Q11/1.6 -> 347.18174 | W11: =R11/1.6 -> 389.31227 | X11: =S11/1.6 -> 431.44281 | Y11: 0.01 | Z11: =U11/1.6 -> 191.26736 | AA11: =V11/1.6 -> 216.98859 | AB11: =W11/1.6 -> 243.32017 | AC11: =X11/1.6 -> 269.65176
C12: 40X50 | D12: =Plan1!$C$10+Plan2!G11 -> 1407.3359 | E12: =Plan1!$C$11+Plan2!G11 -> 1575.9026 | F12: =Plan1!$C$12+Plan2!G11 -> 1748.4692 | G12: =Plan1!$C$13+Plan2!G11 -> 1921.0359 | H12: 0.01 | I12: 40X50 | J12: =D12/1.6 -> 879.58494 | K12: =E12/1.6 -> 984.9391 | L12: =F12/1.6 -> 1092.7933 | M12: =G12/1.6 -> 1200.6474 | O12: 40X50 | P12: =J12/1.6 -> 549.74058 | Q12: =K12/1.6 -> 615.58694 | R12: =L12/1.6 -> 682.99579 | S12: =M12/1.6 -> 750.40465 | T12: 40X60 | U12: =P12/1.6 -> 343.58787 | V12: =Q12/1.6 -> 384.74184 | W12: =R12/1.6 -> 426.87237 | X12: =S12/1.6 -> 469.0029 | Y12: 0.01 | Z12: =U12/1.6 -> 214.74242 | AA12: =V12/1.6 -> 240.46365 | AB12: =W12/1.6 -> 266.79523 | AC12: =X12/1.6 -> 293.12682
C13: 40X60 | D13: =Plan1!$C$10+Plan2!G12 -> 1653.4897 | E13: =Plan1!$C$11+Plan2!G12 -> 1822.0564 | F13: =Plan1!$C$12+Plan2!G12 -> 1994.6231 | G13: =Plan1!$C$13+Plan2!G12 -> 2167.1897 | H13: 0.01 | I13: 40X60 | J13: =D13/1.6 -> 1033.4311 | K13: =E13/1.6 -> 1138.7853 | L13: =F13/1.6 -> 1246.6394 | M13: =G13/1.6 -> 1354.4936 | O13: 40X60 | P13: =J13/1.6 -> 645.89443 | Q13: =K13/1.6 -> 711.74079 | R13: =L13/1.6 -> 779.14964 | S13: =M13/1.6 -> 846.55849 | T13: 45X60 | U13: =P13/1.6 -> 403.68402 | V13: =Q13/1.6 -> 444.83799 | W13: =R13/1.6 -> 486.96852 | X13: =S13/1.6 -> 529.09906 | Y13: 0.01 | Z13: =U13/1.6 -> 252.30251 | AA13: =V13/1.6 -> 278.02374 | AB13: =W13/1.6 -> 304.35533 | AC13: =X13/1.6 -> 330.68691
C14: 45x60 | D14: =Plan1!$C$10+Plan2!G13 -> 1838.1051 | E14: =Plan1!$C$11+Plan2!G13 -> 2006.6718 | F14: =Plan1!$C$12+Plan2!G13 -> 2179.2385 | G14: =Plan1!$C$13+Plan2!G13 -> 2351.8051 | I14: 45x60 | J14: =D14/1.6 -> 1148.8157 | K14: =E14/1.6 -> 1254.1699 | L14: =F14/1.6 -> 1362.024 | M14: =G14/1.6 -> 1469.8782 | O14: 45x60 | P14: =J14/1.6 -> 718.00982 | Q14: =K14/1.6 -> 783.85617 | R14: =L14/1.6 -> 851.26502 | S14: =M14/1.6 -> 918.67388 | U14: =P14/1.6 -> 448.75613 | V14: =Q14/1.6 -> 489.91011 | W14: =R14/1.6 -> 532.04064 | X14: =S14/1.6 -> 574.17117 | Z14: =U14/1.6 -> 280.47258 | AA14: =V14/1.6 -> 306.19382 | AB14: =W14/1.6 -> 332.5254 | AC14: =X14/1.6 -> 358.85698
B16: CAMISETA | C16: 30 X 32 | D16: =Plan1!C10+Plan2!G15 -> 531.02821 | E16: =Plan1!C11+Plan2!G15 -> 699.59487 | F16: =Plan1!C12+Plan2!G15 -> 872.16154 | G16: =Plan1!C13+Plan2!G15 -> 1044.7282 | H16: 0.005 | I16: 30 X 32 | J16: =D16/1.6 -> 331.89263 | K16: =E16/1.6 -> 437.24679 | L16: =F16/1.6 -> 545.10096 | M16: =G16/1.6 -> 652.95513 | N16: CAMISETA | O16: 30 X 32 | P16: =J16/1.6 -> 207.43289 | Q16: =K16/1.6 -> 273.27925 | R16: =L16/1.6 -> 340.6881 | S16: =M16/1.6 -> 408.09696 | T16: 30 X 32 | U16: =P16/1.6 -> 129.64556 | V16: =Q16/1.6 -> 170.79953 | W16: =R16/1.6 -> 212.93006 | X16: =S16/1.6 -> 255.0606 | Y16: 0.005 | Z16: =U16/1.6 -> 81.028474 | AA16: =V16/1.6 -> 106.74971 | AB16: =W16/1.6 -> 133.08129 | AC16: =X16/1.6 -> 159.41287
C17: 30 X 45 | D17: =Plan1!C10+Plan2!G16 -> 675.02821 | E17: =Plan1!C11+Plan2!G16 -> 843.59487 | F17: =Plan1!C12+Plan2!G16 -> 1016.1615 | G17: =Plan1!C13+Plan2!G16 -> 1188.7282 | H17: 0.005 | I17: 30 X 40 | J17: =D17/1.6 -> 421.89263 | K17: =E17/1.6 -> 527.24679 | L17: =F17/1.6 -> 635.10096 | M17: =G17/1.6 -> 742.95513 | O17: 30 X 40 | P17: =J17/1.6 -> 263.68289 | Q17: =K17/1.6 -> 329.52925 | R17: =L17/1.6 -> 396.9381 | S17: =M17/1.6 -> 464.34696 | T17: 30 X 40 | U17: =P17/1.6 -> 164.80181 | V17: =Q17/1.6 -> 205.95578 | W17: =R17/1.6 -> 248.08631 | X17: =S17/1.6 -> 290.21685 | Y17: 0.005 | Z17: =U17/1.6 -> 103.00113 | AA17: =V17/1.6 -> 128.72236 | AB17: =W17/1.6 -> 155.05395 | AC17: =X17/1.6 -> 181.38553
C18: 40 X 50 | D18: =Plan1!C10+Plan2!G17 -> 915.02821 | E18: =Plan1!C11+Plan2!G17 -> 1083.5949 | F18: =Plan1!C12+Plan2!G17 -> 1256.1615 | G18: =Plan1!C13+Plan2!G17 -> 1428.7282 | H18: 0.005 | I18: 40 X 50 | J18: =D18/1.6 -> 571.89263 | K18: =E18/1.6 -> 677.24679 | L18: =F18/1.6 -> 785.10096 | M18: =G18/1.6 -> 892.95513 | O18: 40 X 50 | P18: =J18/1.6 -> 357.43289 | Q18: =K18/1.6 -> 423.27925 | R18: =L18/1.6 -> 490.6881 | S18: =M18/1.6 -> 558.09696 | T18: 40 X 50 | U18: =P18/1.6 -> 223.39556 | V18: =Q18/1.6 -> 264.54953 | W18: =R18/1.6 -> 306.68006 | X18: =S18/1.6 -> 348.8106 | Y18: 0.005 | Z18: =U18/1.6 -> 139.62222 | AA18: =V18/1.6 -> 165.34346 | AB18: =W18/1.6 -> 191.67504 | AC18: =X18/1.6 -> 218.00662
C19: 40 X 60 | D19: =Plan1!C10+Plan2!G18 -> 1062.7205 | E19: =Plan1!C11+Plan2!G18 -> 1231.2872 | F19: =Plan1!C12+Plan2!G18 -> 1403.8538 | G19: =Plan1!C13+Plan2!G18 -> 1576.4205 | H19: 0.005 | I19: 40 X 60 | J19: =D19/1.6 -> 664.20032 | K19: =E19/1.6 -> 769.55449 | L19: =F19/1.6 -> 877.40865 | M19: =G19/1.6 -> 985.26282 | O19: 40 X 60 | P19: =J19/1.6 -> 415.1252 | Q19: =K19/1.6 -> 480.97155 | R19: =L19/1.6 -> 548.38041 | S19: =M19/1.6 -> 615.78926 | T19: 40 X 60 | U19: =P19/1.6 -> 259.45325 | V19: =Q19/1.6 -> 300.60722 | W19: =R19/1.6 -> 342.73776 | X19: =S19/1.6 -> 384.86829 | Y19: 0.005 | Z19: =U19/1.6 -> 162.15828 | AA19: =V19/1.6 -> 187.87951 | AB19: =W19/1.6 -> 214.2111 | AC19: =X19/1.6 -> 240.54268
C20: 50 X 70 | D20: =Plan1!C10+Plan2!G19 -> 1253.4897 | E20: =Plan1!C11+Plan2!G19 -> 1422.0564 | F20: =Plan1!C12+Plan2!G19 -> 1594.6231 | G20: =Plan1!C13+Plan2!G19 -> 1767.1897 | H20: 0.005 | I20: 50 X 70 | J20: =D20/1.6 -> 783.43109 | K20: =E20/1.6 -> 888.78526 | L20: =F20/1.6 -> 996.63942 | M20: =G20/1.6 -> 1104.4936 | O20: 50 X 70 | P20: =J20/1.6 -> 489.64443 | Q20: =K20/1.6 -> 555.49079 | R20: =L20/1.6 -> 622.89964 | S20: =M20/1.6 -> 690.30849 | T20: 50 X 70 | U20: =P20/1.6 -> 306.02777 | V20: =Q20/1.6 -> 347.18174 | W20: =R20/1.6 -> 389.31227 | X20: =S20/1.6 -> 431.44281 | Y20: 0.005 | Z20: =U20/1.6 -> 191.26736 | AA20: =V20/1.6 -> 216.98859 | AB20: =W20/1.6 -> 243.32017 | AC20: =X20/1.6 -> 269.65176
C21: 60 X 80 | D21: =Plan1!C10+Plan2!G20 -> 1653.4897 | E21: =Plan1!C11+Plan2!G20 -> 1822.0564 | F21: =Plan1!C12+Plan2!G20 -> 1994.6231 | G21: =Plan1!C13+Plan2!G20 -> 2167.1897 | H21: 0.005 | I21: 60 X 80 | J21: =D21/1.6 -> 1033.4311 | K21: =E21/1.6 -> 1138.7853 | L21: =F21/1.6 -> 1246.6394 | M21: =G21/1.6 -> 1354.4936 | O21: 60 X 80 | P21: =J21/1.6 -> 645.89443 | Q21: =K21/1.6 -> 711.74079 | R21: =L21/1.6 -> 779.14964 | S21: =M21/1.6 -> 846.55849 | T21: 60 X 80 | U21: =P21/1.6 -> 403.68402 | V21: =Q21/1.6 -> 444.83799 | W21: =R21/1.6 -> 486.96852 | X21: =S21/1.6 -> 529.09906 | Y21: 0.005 | Z21: =U21/1.6 -> 252.30251 | AA21: =V21/1.6 -> 278.02374 | AB21: =W21/1.6 -> 304.35533 | AC21: =X21/1.6 -> 330.68691
C22: 45 X 60 | D22: =Plan1!C10+Plan2!G21 -> 1173.4897 | E22: =Plan1!C11+Plan2!G21 -> 1342.0564 | F22: =Plan1!C12+Plan2!G21 -> 1514.6231 | G22: =Plan1!C13+Plan2!G21 -> 1687.1897 | H22: 0.005 | I22: 45 x 60 | J22: =D22/1.6 -> 733.43109 | K22: =E22/1.6 -> 838.78526 | L22: =F22/1.6 -> 946.63942 | M22: =G22/1.6 -> 1054.4936 | O22: 45 X 60 | P22: =J22/1.6 -> 458.39443 | Q22: =K22/1.6 -> 524.24079 | R22: =L22/1.6 -> 591.64964 | S22: =M22/1.6 -> 659.05849 | T22: 45 X 60 | U22: =P22/1.6 -> 286.49652 | V22: =Q22/1.6 -> 327.65049 | W22: =R22/1.6 -> 369.78102 | X22: =S22/1.6 -> 411.91156 | Y22: 0.005 | Z22: =U22/1.6 -> 179.06032 | AA22: =V22/1.6 -> 204.78156 | AB22: =W22/1.6 -> 231.11314 | AC22: =X22/1.6 -> 257.44472
B25: 35x50 | C25: 1000 | D25: 905 | E25: =D25/C25 -> 0.905 | F25: 1 cor | G25: 1000 | H25: 30x40 | I25: 7 cores | J25: 1756
B26: 30x40 | C26: 1000 | D26: 670 | E26: =D26/C26 -> 0.67 | F26: 1 cor | G26: 500 | J26: =J25/1.6 -> 1097.5
B27: 35x50 | C27: 1000 | D27: 1505 | E27: =D27/C27 -> 1.505 | F27: 5 cores | G27: 250 | J27: =J26/1.6 -> 685.9375
B28: 30x40 | C28: 1000 | D28: 1269 | E28: =D28/C28 -> 1.269 | F28: 5 cores
D29: 1269 | I29: 1114
B30: cores | C30: Tamanho | D30: vlr.tot | E30: quant | I30: 155 | K30: MAIN | L30: 40
B31: 1 cor | C31: 35x50 | D31: 2000 | E31: =D31/E25 -> 2209.9448 | I31: =SUM(I29:I30) -> 1269 | K31: TECNOPLAST | L31: 43
B32: 1 cor | C32: 30x40 | D32: 2000 | E32: =D32/E26 -> 2985.0746 | K32: 2 IRMÃO | L32: 40
B33: 5 cores | C33: 35x50 | D33: 2000 | E33: =D33/E27 -> 1328.9037 | K33: total mais | L33: 35
B34: 5 cores | C34: 30x40 | D34: 2000 | E34: =D34/E28 -> 1576.0441
B37: orçamento menor preço

Sheet Planilha2

Sheet Planilha1
